{
    "Version": "1.2",
    "Data": {
        "Source": "c:\\projects\\glbutil\\plugins\\tfgltfcore\\source\\tfgltfdraco\\io\\obj_encoder.cc",
        "ProvidedModule": "",
        "PCH": "c:\\projects\\glbutil\\intermediate\\build\\win64\\glbutileditor\\development\\engine\\sharedpch.engine.shadowerrors.h.pch",
        "Includes": [
            "c:\\projects\\glbutil\\plugins\\tfgltfcore\\intermediate\\build\\win64\\unrealeditor\\development\\tfgltfdraco\\definitions.tfgltfdraco.h",
            "c:\\projects\\glbutil\\plugins\\tfgltfcore\\source\\tfgltfdraco\\io\\obj_encoder.h",
            "c:\\projects\\glbutil\\plugins\\tfgltfcore\\source\\tfgltfdraco\\core\\encoder_buffer.h",
            "c:\\projects\\glbutil\\plugins\\tfgltfcore\\source\\tfgltfdraco\\core\\bit_utils.h",
            "c:\\program files (x86)\\windows kits\\10\\include\\10.0.19041.0\\ucrt\\inttypes.h",
            "c:\\projects\\glbutil\\plugins\\tfgltfcore\\source\\tfgltfdraco\\core\\macros.h",
            "c:\\program files\\microsoft visual studio\\2022\\community\\vc\\tools\\msvc\\14.33.31629\\include\\cassert",
            "c:\\program files (x86)\\windows kits\\10\\include\\10.0.19041.0\\ucrt\\assert.h",
            "c:\\projects\\glbutil\\plugins\\tfgltfcore\\source\\tfgltfdraco\\draco_features.h",
            "c:\\projects\\glbutil\\plugins\\tfgltfcore\\source\\tfgltfdraco\\mesh\\corner_table.h",
            "c:\\program files\\microsoft visual studio\\2022\\community\\vc\\tools\\msvc\\14.33.31629\\include\\array",
            "c:\\projects\\glbutil\\plugins\\tfgltfcore\\source\\tfgltfdraco\\attributes\\geometry_indices.h",
            "c:\\projects\\glbutil\\plugins\\tfgltfcore\\source\\tfgltfdraco\\core\\draco_index_type.h",
            "c:\\projects\\glbutil\\plugins\\tfgltfcore\\source\\tfgltfdraco\\core\\draco_index_type_vector.h",
            "c:\\projects\\glbutil\\plugins\\tfgltfcore\\source\\tfgltfdraco\\mesh\\valence_cache.h",
            "c:\\projects\\glbutil\\plugins\\tfgltfcore\\source\\tfgltfdraco\\mesh\\mesh.h",
            "c:\\projects\\glbutil\\plugins\\tfgltfcore\\source\\tfgltfdraco\\core\\hash_utils.h",
            "c:\\projects\\glbutil\\plugins\\tfgltfcore\\source\\tfgltfdraco\\core\\status.h",
            "c:\\program files\\microsoft visual studio\\2022\\community\\vc\\tools\\msvc\\14.33.31629\\include\\string",
            "c:\\projects\\glbutil\\plugins\\tfgltfcore\\source\\tfgltfdraco\\compression\\draco_compression_options.h",
            "c:\\projects\\glbutil\\plugins\\tfgltfcore\\source\\tfgltfdraco\\material\\material_library.h",
            "c:\\program files\\microsoft visual studio\\2022\\community\\vc\\tools\\msvc\\14.33.31629\\include\\map",
            "c:\\program files\\microsoft visual studio\\2022\\community\\vc\\tools\\msvc\\14.33.31629\\include\\xtree",
            "c:\\projects\\glbutil\\plugins\\tfgltfcore\\source\\tfgltfdraco\\material\\material.h",
            "c:\\projects\\glbutil\\plugins\\tfgltfcore\\source\\tfgltfdraco\\core\\vector_d.h",
            "c:\\projects\\glbutil\\plugins\\tfgltfcore\\source\\tfgltfdraco\\texture\\texture_library.h",
            "c:\\projects\\glbutil\\plugins\\tfgltfcore\\source\\tfgltfdraco\\texture\\texture.h",
            "c:\\projects\\glbutil\\plugins\\tfgltfcore\\source\\tfgltfdraco\\io\\image_compression_options.h",
            "c:\\projects\\glbutil\\plugins\\tfgltfcore\\source\\tfgltfdraco\\texture\\source_image.h",
            "c:\\projects\\glbutil\\plugins\\tfgltfcore\\source\\tfgltfdraco\\texture\\texture_map.h",
            "c:\\projects\\glbutil\\plugins\\tfgltfcore\\source\\tfgltfdraco\\texture\\texture_transform.h",
            "c:\\projects\\glbutil\\plugins\\tfgltfcore\\source\\tfgltfdraco\\mesh\\mesh_features.h",
            "c:\\projects\\glbutil\\plugins\\tfgltfcore\\source\\tfgltfdraco\\mesh\\mesh_indices.h",
            "c:\\projects\\glbutil\\plugins\\tfgltfcore\\source\\tfgltfdraco\\metadata\\structural_metadata.h",
            "c:\\projects\\glbutil\\plugins\\tfgltfcore\\source\\tfgltfdraco\\metadata\\property_table.h",
            "c:\\projects\\glbutil\\plugins\\tfgltfcore\\source\\tfgltfdraco\\point_cloud\\point_cloud.h",
            "c:\\projects\\glbutil\\plugins\\tfgltfcore\\source\\tfgltfdraco\\attributes\\point_attribute.h",
            "c:\\projects\\glbutil\\plugins\\tfgltfcore\\source\\tfgltfdraco\\attributes\\attribute_transform_data.h",
            "c:\\projects\\glbutil\\plugins\\tfgltfcore\\source\\tfgltfdraco\\attributes\\attribute_transform_type.h",
            "c:\\projects\\glbutil\\plugins\\tfgltfcore\\source\\tfgltfdraco\\core\\data_buffer.h",
            "c:\\projects\\glbutil\\plugins\\tfgltfcore\\source\\tfgltfdraco\\core\\draco_types.h",
            "c:\\projects\\glbutil\\plugins\\tfgltfcore\\source\\tfgltfdraco\\attributes\\geometry_attribute.h",
            "c:\\projects\\glbutil\\plugins\\tfgltfcore\\source\\tfgltfdraco\\core\\bounding_box.h",
            "c:\\projects\\glbutil\\plugins\\tfgltfcore\\source\\tfgltfdraco\\metadata\\geometry_metadata.h",
            "c:\\projects\\glbutil\\plugins\\tfgltfcore\\source\\tfgltfdraco\\metadata\\metadata.h",
            "c:\\projects\\glbutil\\plugins\\tfgltfcore\\source\\tfgltfdraco\\io\\file_writer_factory.h",
            "c:\\projects\\glbutil\\plugins\\tfgltfcore\\source\\tfgltfdraco\\io\\file_writer_interface.h",
            "c:\\projects\\glbutil\\plugins\\tfgltfcore\\source\\tfgltfdraco\\mesh\\mesh_misc_functions.h"
        ],
        "ImportedModules": [],
        "ImportedHeaderUnits": []
    }
}